<?xml version="1.0" encoding="windows-1250"?>
<root>
<sprache value="Slovenian" />
<raum_auswahl value="izbira prostora"/>
<raum value="prostor"/>
<watt value="wattov"/>
<grad value="°C"/>
<raum_watt value="zahteva po toploti v prostoru"/>
<temp value="temperatura"/>
<temp_vor value="temperatura predtoka"/>
<temp_rueck value="temperatura povratka"/>
<temp_raum value="sobna temperatura"/>
<leistung value="toplotna moè"/>
<hoehe value="višina"/>
<laenge value="dolžina"/>
<typ value="tip"/>
<artno value="Št. izdelka."/>
<prodno value="Št. izdelka."/>
<kurztext value="kratko besedilo"/>
<preis value="cena"/>
<rabatt value="viš. rabata"/>
<hoehe_1 value="300" />   
<hoehe_2 value="400" />
<hoehe_3 value="500" />
<hoehe_6 value="550" />
<hoehe_4 value="600" />
<hoehe_5 value="900" />   
<hoehe_7 value="950" />
<hoehe_8 value="1400" />
<hoehe_9 value="1600" />   
<hoehe_10 value="1800" />
<hoehe_11 value="2000" /> 
<hoehe_12 value="2200" /> 
<hoehe_13 value="2400" /> 
<hoehe_einheit value="mm" />
<laenge_1 value="400" />
<laenge_2 value="500" />
<laenge_3 value="600" />
<laenge_4 value="700" />
<laenge_5 value="800" />
<laenge_6 value="900" />
<laenge_7 value="1000" />  
<laenge_16 value="1100" />
<laenge_8 value="1200" /> 
<laenge_17 value="1300" />
<laenge_9 value="1400" />  
<laenge_18 value="1500" />
<laenge_10 value="1600" />
<laenge_11 value="1800" />
<laenge_12 value="2000" />
<laenge_13 value="2300" />
<laenge_14 value="2600" /> 
<laenge_15 value="3000" />
<laenge_20 value="300" />
<laenge_21 value="400" />
<laenge_22 value="500" />
<laenge_23 value="600" />
<laenge_24 value="700" />
<laenge_25 value="900" />  
<raum_wohn value="dnevna soba"/>
<raum_kind value="otroška soba"/>
<raum_schlaf value="spalnica"/>
<raum_bad value="kopalnica"/>
<raum_flur value="hodnik"/>
<raum_treppe value="stopnišèe"/>
<raum_kueche value="kuhinja"/>
<raum_wc value="WC"/>
<layer_main value="izbira"/>
<layer_zub_spez value="posebna dodatna oprema"/>
<layer_zub_allg value="splošna dodatna oprema"/>
<layer_info value="Informacije o izdelku"/>
<layer_report value="tehn. poroèilo"/>
<layer_k_report value="prod. poroèilo"/>
<pos value="poz."/>
<heizk value="grelno telo"/>
<einstell value="nastavitveno število"/>
<ventil value="ventil"/>
<leistung_report value="topl. moè"/>
<warenkorb value="košarica z izdelki"/>
<zu_warenkorb value="dodaj v košarico"/>
<projekt value="projekt"/>
<zu_projekt value="dodaj v projekt"/>
<bestand value="izraèun iz zaloge"/>
<bez value="oznaka"/>
<preis_currency value="cena v EUR"/>
<stueck value="kos"/>
<speichern value="Shrani"/>
<ventil_kopf value="termostatska glava"/>
<ventil_fluessig value="element tipala tekoèine"/>
<ventil_gas value="element tipala plina"/>
<ventil_pre value="Izraèun nastavitve ventila za hidravlièno izravnavo"/>
<ventil_druck value="dif. tlak ventila"/>
<ventil_kv value="vrednost kv"/>
<ventil_ventil value="nastavitveno število / vgradni ventil"/>
<ventil_liefer value="je v obsegu dobave. prednastavitev ventila je mogoèe po potrebi spremeniti preprosto z vrtenjem."/>
<ventil_liefer2 value="Èe je treba uporabiti drugi vgradni ventil (N namesto U oz. U namesto N), ga je treba naroèiti posebej."/>
<ventil_laut value="Èe diferencialni tlak presega 200 mbar, lahko prihaja do šumenja!"/>
<ventil_error_n value="Vrednost kv je prevelika – prosim prilagodite razporo ali diferencialni tlak ventila!"/>
<ventil_error_u value="Vrednost kv je prevelika – prosim izberite ventil N ali prilagodite razporo!"/>
<ventil_einbau value="vgradni ventil"/>
<ventil_einbau_vorein value="vgradni ventil s predhodno nastavitvijo"/>
<keine_angabe value="ni podatka"/>
<ja value="Da"/>
<nein value="Ne"/>
<ok value="OK"/>
<abbrechen value="Preklic"/>
<warning value="Opozorilo"/>
<set value="Uporabi"/>
<export_pdf value="Izvozi kot PDF"/>
<export_bud value="Shrani"/>
<export_ugs value="Izvozi kot UGS"/>
<import_bud value="Naloži"/>
<zurueck value="Nazaj"/>
<bestand_bedarf value="Ocena potrebe po toploti"/>
<bestand_radiator value="Liti ali jekleni radiatorji"/>
<msg_bestand_pre value="Izberite osnovo za izraèun zaloge!"/>
<msg_bestand_bedarf value="Za izraèun približne potrebe po toploti za vašo stanovanjsko stavbo v naslednji tabeli izberite leto gradnje vaše hiše in ustrezno vrednost za potrebo po toploti. Izraèun se naredi na podlagi množenja z velikostjo prostora, ki ga je treba ogrevati.  ta ocena je zelo nenatanèna zaradi razliènih obmoèij potreb po toploti v stavbah. Obe prejšnji možnosti zagotavljata veliko natanènejše rezultate in ju je zaradi tega bolj priporoèljivo uporabiti. Z gumbom Uporabi se izraèunana vrednost prenese v polje Zahteva po toploti v prostoru. "/>
<msg_bestand_radiator value="Na podlagi števila vgrajenih [b]litih ali jeklenih radiatorjev[*b] je mogoèe grobo oceniti zahtevo po toploti v prostoru. Z gumbom Uporabi se izraèunana vrednost prenese v polje Zahteva po toploti v prostoru. "/>
<msg_druck_warning value="Vrednost diferencialnega tlaka je omejena na 200 mbar!"/>
<msg_leistung_warning value="Toplotna moè radiatorjev je manjša od vnesene zahteve po toploti v prostoru! Ali nja vseeno uporabim vrednost?"/>
<msg_empty_output value="Prosim, izberite radiator!"/>
<msg_invalid_product value="Vnesena številka izdlka ne obstaja!"/>
<msg_toReport value="Prosim, vnesite število kosov za prodajno poroèilo. Èe boste kliknili na gumb Preklièi, izdelek ne bo vkljuèen v nobeno poroèilo!"/>
<msg_removeReport value="Ali ste preprièani, da želite izbrani izdelek odstraniti iz tehniènega poroèila?"/>
<msg_removeKReport value="Ali ste preprièani, da želite izbrani izdelek odstraniti iz prodajnega poroèila?"/>
<msg_toCart value="Ali želite izdelek dodati v košarico in tehnièno poroèilo? Prosim, vnesite število kosov izdelka!"/>
<msg_toProject value="Ali želite izdelek dodati v projekt? S klikom na gumb Projekt lahko znova urejate ustvarjeni Projekt! Prosim, vnesite število kosov izdelka!"/>
<msg_amount_null value="Prosim vnesite število izdelkov, veèje od 0!"/>
<msg_updateRoom value="Vnesite ime za prostor!"/>
<msg_updateStueck value="Vnesite število kosov izdelka!"/>
<msg_ugs_bud value="Prosim, vnesite oznako Buderus iz svojega prodajnega programa (najv. 4 znaki)"/>
<bestand_baujahr value ="rok budovy" />
<bestand_raumgroesse value ="veľkosť izby" />
<bestand_hohe value ="výška mm" />
<bestand_tiefe value ="hĺbka mm" />
<bestand_systemtemp value ="Teplota systému (old)" />
<bestand_gliederanzahl value ="počet segmentov" />
<imprint value="odtlačok"/>
</root>